Metadata-Version: 1.1
Name: httpagentparser
Version: 1.3.0
Summary: Extracts OS Browser etc information from http user agent string
Home-page: https://github.com/shon/httpagentparser
Author: Shekhar Tiwatne
Author-email: pythonic@gmail.com
License: http://www.opensource.org/licenses/mit-license.php
Platform: UNKNOWN
Classifier: Programming Language :: Python
Classifier: Programming Language :: Python :: 3
